ai_search_adm/__about__.py
ai_search_adm/__init__.py
ai_search_adm/cli.py
ai_search_adm-0.9.0b3.dist-info/METADATA
ai_search_adm-0.9.0b3.dist-info/WHEEL
ai_search_adm-0.9.0b3.dist-info/entry_points.txt
ai_search_adm-0.9.0b3.dist-info/licenses/LICENSE
ai_search_adm-0.9.0b3.dist-info/RECORD
