Metadata-Version: 2.4
Name: ai-search-adm
Version: 0.9.0b3
Summary: Administration tool for Azure AI Search indexes
Project-URL: Documentation, https://github.com/domibies/ai-search-adm#readme
Project-URL: Issues, https://github.com/domibies/ai-search-adm/issues
Project-URL: Source, https://github.com/domibies/ai-search-adm
Project-URL: Homepage, https://github.com/domibies/ai-search-adm
Author: domibies
License-Expression: MIT
License-File: LICENSE
Keywords: administration,azure,cli,search
Classifier: Development Status :: 4 - Beta
Classifier: Intended Audience :: Developers
Classifier: Intended Audience :: System Administrators
Classifier: License :: OSI Approved :: MIT License
Classifier: Operating System :: OS Independent
Classifier: Programming Language :: Python
Classifier: Programming Language :: Python :: 3.11
Classifier: Programming Language :: Python :: 3.12
Classifier: Programming Language :: Python :: 3.13
Classifier: Programming Language :: Python :: Implementation :: CPython
Classifier: Topic :: Internet :: WWW/HTTP :: Indexing/Search
Classifier: Topic :: System :: Systems Administration
Classifier: Topic :: Utilities
Requires-Python: >=3.11
Requires-Dist: azure-identity>=1.15.0
Requires-Dist: azure-search-documents>=11.4.0
Requires-Dist: click>=8.0.0
Requires-Dist: rich>=13.0.0
Requires-Dist: typer>=0.9.0
Provides-Extra: dev
Requires-Dist: black>=25.1.0; extra == 'dev'
Requires-Dist: mypy>=1.0.0; extra == 'dev'
Requires-Dist: pytest-cov>=4.0.0; extra == 'dev'
Requires-Dist: pytest>=7.0.0; extra == 'dev'
Requires-Dist: ruff>=0.1.0; extra == 'dev'
